soypedroamaya/__init__.py
soypedroamaya/bunit/__init__.py
soypedroamaya/bunit/concept/__init__.py
soypedroamaya/bunit/concept/domain/__init__.py
soypedroamaya/bunit/concept/domain/calculator.py
donpeterlibs-0.0.0.dist-info/LICENSE
donpeterlibs-0.0.0.dist-info/METADATA
donpeterlibs-0.0.0.dist-info/WHEEL
donpeterlibs-0.0.0.dist-info/top_level.txt
donpeterlibs-0.0.0.dist-info/RECORD
